multicv2resize/README.MD
multicv2resize/__init__.py
multicv2resize/requirements.txt
multicv2resize/thirdparty.json
multicv2resize-0.10.dist-info/LICENSE.rst
multicv2resize-0.10.dist-info/METADATA
multicv2resize-0.10.dist-info/WHEEL
multicv2resize-0.10.dist-info/top_level.txt
multicv2resize-0.10.dist-info/RECORD
