Metadata-Version: 2.1
Name: multicv2resize
Version: 0.10
Summary: Parallelized image resizing function using OpenCV and multiprocessing
Home-page: https://github.com/hansalemaos/multicv2resize
Author: Johannes Fischer
Author-email: aulasparticularesdealemaosp@gmail.com
License: MIT
Keywords: multiprocessing,resize,image
Classifier: Development Status :: 4 - Beta
Classifier: Programming Language :: Python :: 3 :: Only
Classifier: Programming Language :: Python :: 3.10
Classifier: Topic :: Software Development :: Libraries :: Python Modules
Classifier: Topic :: Utilities
License-File: LICENSE.rst
Requires-Dist: a-cv2-easy-resize
Requires-Dist: a-cv-imwrite-imread-plus
Requires-Dist: multiprocnomain
Requires-Dist: numpy
Requires-Dist: opencv-python
